unsonic
