Metadata-Version: 1.2
Name: unsonic
Version: 0.1.3
Summary: Unsonic, the un-Subsonic music server.
Home-page: https://github.com/redshodan/unsonic
Author: Chris Newton
Author-email: redshodan@gmail.com
License: GPLv2
Keywords: unsonic,mishmash,eyed3,web,wsgi,bfg,pylons,pyramid
Platform: Any
Classifier: Intended Audience :: End Users/Desktop
Classifier: Operating System :: POSIX
Classifier: Natural Language :: English
Classifier: Programming Language :: Python
Classifier: Framework :: Pyramid
Classifier: Topic :: Internet :: WWW/HTTP
Classifier: Topic :: Internet :: WWW/HTTP :: WSGI :: Application
Classifier: Programming Language :: Python :: 3.6
Classifier: Programming Language :: Python :: 3.7
Classifier: Development Status :: 3 - Alpha
Requires-Python: >=3.6
